{"title":"JavaScript: Vite 是一种新型前端构建工具，能够显著提升前端开发体验","slug":"2022/js-vite","date":"2022-08-23T16:31:37.000Z","updated":"2023-03-13T16:23:43.135Z","comments":true,"path":"api/articles/2022/js-vite.json","excerpt":"主要由两部分组成：一个开发服务器，它基于 原生 ES 模块 提供了 丰富的内建功能，如速度快到惊人的 模块热更新（HMR）。一套构建指令，它使用 Rollup 打包你的代码，并且它是预配置的，可输出用于生产环境的高度优化过的静态资源。","covers":null,"content":"<h4 id=\"主要由两部分组成：\">主要由两部分组成：</h4>\n<p>一个开发服务器，它基于 原生 ES 模块 提供了 丰富的内建功能，如速度快到惊人的 模块热更新（HMR）。</p>\n<p>一套构建指令，它使用 Rollup 打包你的代码，并且它是预配置的，可输出用于生产环境的高度优化过的静态资源。</p>\n<span id=\"more\"></span>\n","more":"","categories":[{"name":"2022","path":"api/categories/2022.json"}],"tags":[{"name":"JavaScript","path":"api/tags/JavaScript.json"},{"name":"Vite","path":"api/tags/Vite.json"}]}