{"title":"JSON 是存储和交换文本信息的语法，类似 XML","slug":"2022/json","date":"2022-08-28T10:09:17.000Z","updated":"2022-08-28T10:09:55.429Z","comments":true,"path":"api/articles/2022/json.json","excerpt":null,"covers":null,"content":"<h3 id=\"简介\">简介</h3>\n<p>JSON: JavaScript Object Notation(JavaScript 对象表示法)</p>\n<p>JSON 是存储和交换文本信息的语法，类似 XML。</p>\n<p>JSON 比 XML 更小、更快，更易解析。</p>\n<p>JSON 易于人阅读和编写。</p>\n<p>C、Python、C++、Java、PHP、Go等编程语言都支持 JSON。</p>\n","more":"<h3 id=\"简介\">简介</h3>\n<p>JSON: JavaScript Object Notation(JavaScript 对象表示法)</p>\n<p>JSON 是存储和交换文本信息的语法，类似 XML。</p>\n<p>JSON 比 XML 更小、更快，更易解析。</p>\n<p>JSON 易于人阅读和编写。</p>\n<p>C、Python、C++、Java、PHP、Go等编程语言都支持 JSON。</p>\n","categories":[{"name":"2022","path":"api/categories/2022.json"}],"tags":[{"name":"json","path":"api/tags/json.json"}]}